ossreport/__init__.py
ossreport/__version__.py
ossreport/main.py
ossreport/analyzer/__init__.py
ossreport/analyzer/analyzer.py
ossreport/builder/__init__.py
ossreport/builder/builder.py
ossreport/cmd/__init__.py
ossreport/cmd/argument.py
ossreport/cmd/banner.py
ossreport/config/__init__.py
ossreport/config/config.py
ossreport/config/config.yml
ossreport/data/license.json
ossreport/logger/__init__.py
ossreport/logger/logger.py
ossreport/printer/__init__.py
ossreport/printer/printer.py
ossreport/proto/__init__.py
ossreport/proto/proto.py
ossreport-2.0.0.dist-info/LICENSE
ossreport-2.0.0.dist-info/METADATA
ossreport-2.0.0.dist-info/WHEEL
ossreport-2.0.0.dist-info/entry_points.txt
ossreport-2.0.0.dist-info/top_level.txt
ossreport-2.0.0.dist-info/RECORD
