Metadata-Version: 2.1
Name: ossreport
Version: 2.0.0
Summary: SCANOSS Report
Home-page: https://github.com/craftslab/ossreport
Author: Jia Jia
Author-email: angersax@sina.com
License: Apache-2.0
Download-URL: https://github.com/craftslab/ossreport/archive/v2.0.0.tar.gz
Keywords: scanoss,report
Platform: UNKNOWN
Classifier: Development Status :: 3 - Alpha
Classifier: Intended Audience :: Developers
Classifier: Programming Language :: Python :: 3
Classifier: License :: OSI Approved :: Apache Software License
Classifier: Operating System :: OS Independent
License-File: LICENSE
Requires-Dist: black
Requires-Dist: colorama
Requires-Dist: coverage
Requires-Dist: coveralls
Requires-Dist: flake8
Requires-Dist: hypothesis
Requires-Dist: mypy
Requires-Dist: openpyxl
Requires-Dist: pre-commit
Requires-Dist: pytest
Requires-Dist: pyyaml
Requires-Dist: reportlab
Requires-Dist: setuptools
Requires-Dist: twine
Requires-Dist: wheel
